nested_json/__init__.py
nested_json-1.0.1.dist-info/LICENSE
nested_json-1.0.1.dist-info/METADATA
nested_json-1.0.1.dist-info/WHEEL
nested_json-1.0.1.dist-info/top_level.txt
nested_json-1.0.1.dist-info/RECORD
