Metadata-Version: 2.1
Name: nested-json
Version: 1.0.1
Summary: A library to manage JSONs with encoded JSON more effectively (e.g. AWS Event Bridge Events, AWS API Gateway Events)
Home-page: https://github.com/szikszail/nested-json
Author: Laszlo Szikszai
Author-email: sziklaszlo@gmail.com
License: UNKNOWN
Project-URL: Bug Tracker, https://github.com/szikszail/nested-json/issues
Platform: UNKNOWN
Classifier: Programming Language :: Python :: 3
Classifier: License :: OSI Approved :: MIT License
Classifier: Operating System :: OS Independent
Requires-Python: >=3.6
License-File: LICENSE
